TagsAsADatabase/__init__.py
TagsAsADatabase/database.py
AWS_Tags_As_A_DataBase-0.0.1.dist-info/LICENSE
AWS_Tags_As_A_DataBase-0.0.1.dist-info/METADATA
AWS_Tags_As_A_DataBase-0.0.1.dist-info/WHEEL
AWS_Tags_As_A_DataBase-0.0.1.dist-info/top_level.txt
AWS_Tags_As_A_DataBase-0.0.1.dist-info/RECORD
