Metadata-Version: 2.1
Name: AWS-Tags-As-A-DataBase
Version: 0.0.1
Summary: Use AWS Tags As A Key-Value DataBase
Home-page: https://github.com/OrenLeung/AWSTagsAsADatabase
Author: Oren Leung
Author-email: ok2leung@uwaterloo.ca
License: UNKNOWN
Project-URL: Bug Tracker, https://github.com/OrenLeung/AWSTagsAsADatabase/issues
Platform: UNKNOWN
Classifier: Programming Language :: Python :: 3
Classifier: License :: OSI Approved :: MIT License
Classifier: Operating System :: OS Independent
Requires-Python: >=3.6
License-File: LICENSE
Requires-Dist: boto3
